odoo10_addon_sale_partner_incoterm-10.0.1.0.1-py3.8-nspkg.pth
odoo/addons/sale_partner_incoterm/README.rst
odoo/addons/sale_partner_incoterm/__init__.py
odoo/addons/sale_partner_incoterm/__manifest__.py
odoo/addons/sale_partner_incoterm/i18n/ca.po
odoo/addons/sale_partner_incoterm/i18n/de.po
odoo/addons/sale_partner_incoterm/i18n/es.po
odoo/addons/sale_partner_incoterm/i18n/fi.po
odoo/addons/sale_partner_incoterm/i18n/fr.po
odoo/addons/sale_partner_incoterm/i18n/it.po
odoo/addons/sale_partner_incoterm/i18n/nl.po
odoo/addons/sale_partner_incoterm/i18n/sale_partner_incoterm.pot
odoo/addons/sale_partner_incoterm/i18n/sl.po
odoo/addons/sale_partner_incoterm/i18n/tr.po
odoo/addons/sale_partner_incoterm/i18n/zh_CN.po
odoo/addons/sale_partner_incoterm/models/__init__.py
odoo/addons/sale_partner_incoterm/models/res_partner.py
odoo/addons/sale_partner_incoterm/models/sale_order.py
odoo/addons/sale_partner_incoterm/static/description/icon.png
odoo/addons/sale_partner_incoterm/tests/__init__.py
odoo/addons/sale_partner_incoterm/tests/test_sale_partner_incoterm.py
odoo/addons/sale_partner_incoterm/views/res_partner.xml
odoo10_addon_sale_partner_incoterm-10.0.1.0.1.dist-info/METADATA
odoo10_addon_sale_partner_incoterm-10.0.1.0.1.dist-info/WHEEL
odoo10_addon_sale_partner_incoterm-10.0.1.0.1.dist-info/namespace_packages.txt
odoo10_addon_sale_partner_incoterm-10.0.1.0.1.dist-info/top_level.txt
odoo10_addon_sale_partner_incoterm-10.0.1.0.1.dist-info/RECORD
